setup.py
PCA9685_driver.egg-info/PKG-INFO
PCA9685_driver.egg-info/SOURCES.txt
PCA9685_driver.egg-info/dependency_links.txt
PCA9685_driver.egg-info/requires.txt
PCA9685_driver.egg-info/top_level.txt
pca9685_driver/__init__.py
pca9685_driver/device.py
pca9685_driver/tools/__init__.py
pca9685_driver/tools/fake_smbus.py
test/__init__.py
test/test_device.py