Metadata-Version: 1.0
Name: PCA9685-driver
Version: 1.2.0
Summary: Driver module for PCA9685 pwm (LED/Servo) controller
Home-page: https://github.com/voidpp/PCA9685-driver.git
Author: Lajos Santa
Author-email: santa.lajos@coldline.hu
License: UNKNOWN
Platform: UNKNOWN
